tkat/__init__.py
tkat/tkat.py
tkat-0.2.3.dist-info/METADATA
tkat-0.2.3.dist-info/WHEEL
tkat-0.2.3.dist-info/RECORD
